minihatch/__about__.py
minihatch/__init__.py
minihatch-0.0.1.dist-info/METADATA
minihatch-0.0.1.dist-info/WHEEL
minihatch-0.0.1.dist-info/licenses/LICENSE.txt
minihatch-0.0.1.dist-info/RECORD
